odoo/addons/sinli/__init__.py
odoo/addons/sinli/__manifest__.py
odoo/addons/sinli/models/__init__.py
odoo/addons/sinli/models/get_file.py
odoo/addons/sinli/models/sinli_product_template.py
odoo/addons/sinli/static/description/icon.png
odoo/addons/sinli/views/download_file.xml
odoo/addons/sinli/views/export_libro_view.xml
odoo13_addon_sinli-13.0.0.0.3.dist-info/METADATA
odoo13_addon_sinli-13.0.0.0.3.dist-info/WHEEL
odoo13_addon_sinli-13.0.0.0.3.dist-info/top_level.txt
odoo13_addon_sinli-13.0.0.0.3.dist-info/RECORD
