Metadata-Version: 2.1
Name: odoo13-addon-sinli
Version: 13.0.0.0.3
Requires-Python: >=3.5
Requires-Dist: odoo>=13.0a,<13.1dev
Requires-Dist: python-stdnum
Requires-Dist: sinli
Summary: =?utf-8?q?M=C3=B3dulo_para_la_integraci=C3=B3n_de_sinli_en_Odoo=2E?=
Home-page: https://framagit.org/devcontrol
License: OPL-1
Author: Colectivo DEVCONTROL
Classifier: Programming Language :: Python
Classifier: Framework :: Odoo
Classifier: Framework :: Odoo :: 13.0
